{
  "updated_at": "2026-01-26T17:05:07.589+00:00",
  "items": [
    {
      "key": "lao_pattana",
      "name": "หวยลาวพัฒนา",
      "source_url": "https://www.sanook.com/news/laolotto/",
      "fetched_at": "2026-01-26T17:05:10.405+00:00",
      "draws": [
        {
          "draw_date": "2026-01-26",
          "full_number": "0932",
          "top3": "932",
          "top2": "32",
          "bottom2": "32"
        },
        {
          "draw_date": "2026-01-23",
          "full_number": "8401",
          "top3": "401",
          "top2": "01",
          "bottom2": "01"
        },
        {
          "draw_date": "2026-01-21",
          "full_number": "9685",
          "top3": "685",
          "top2": "85",
          "bottom2": "85"
        }
      ]
    },
    {
      "key": "lao_samakkee",
      "name": "ลาวสามัคคี",
      "source_url": "https://www.raakaadee.com/ตรวจหวย-หุ้น/หวยลาวสามัคคี/",
      "fetched_at": "2026-01-26T17:05:15.792+00:00",
      "draws": [
        {
          "draw_date": "2026-01-26",
          "full_number": "02291",
          "top3": "291",
          "top2": "91",
          "bottom2": "22"
        },
        {
          "draw_date": "2026-01-25",
          "full_number": "99506",
          "top3": "506",
          "top2": "06",
          "bottom2": "95"
        },
        {
          "draw_date": "2026-01-24",
          "full_number": "16447",
          "top3": "447",
          "top2": "47",
          "bottom2": "64"
        }
      ]
    },
    {
      "key": "lao_vip",
      "name": "ลาว VIP",
      "source_url": "https://www.raakaadee.com/ตรวจหวย-หุ้น/หวยลาว-VIP/",
      "fetched_at": "2026-01-26T17:05:19.352+00:00",
      "draws": [
        {
          "draw_date": "2026-01-26",
          "full_number": "35014",
          "top3": "014",
          "top2": "14",
          "bottom2": "50"
        },
        {
          "draw_date": "2026-01-25",
          "full_number": "39088",
          "top3": "088",
          "top2": "88",
          "bottom2": "90"
        },
        {
          "draw_date": "2026-01-24",
          "full_number": "37457",
          "top3": "457",
          "top2": "57",
          "bottom2": "74"
        }
      ]
    },
    {
      "key": "lao_star",
      "name": "ลาวสตาร์",
      "source_url": "https://www.raakaadee.com/ตรวจหวย-หุ้น/หวยลาวสตาร์/",
      "fetched_at": "2026-01-26T17:05:23.382+00:00",
      "draws": [
        {
          "draw_date": "2026-01-26",
          "full_number": "49214",
          "top3": "214",
          "top2": "14",
          "bottom2": "49"
        },
        {
          "draw_date": "2026-01-25",
          "full_number": "88028",
          "top3": "028",
          "top2": "28",
          "bottom2": "88"
        },
        {
          "draw_date": "2026-01-24",
          "full_number": "22963",
          "top3": "963",
          "top2": "63",
          "bottom2": "22"
        }
      ]
    },
    {
      "key": "lao_extra",
      "name": "ลาว Extra",
      "source_url": "https://www.raakaadee.com/ตรวจหวย-หุ้น/หวยลาว-Extra/",
      "fetched_at": "2026-01-26T17:05:28.453+00:00",
      "draws": [
        {
          "draw_date": "2026-01-26",
          "full_number": "38049",
          "top3": "049",
          "top2": "49",
          "bottom2": "38"
        },
        {
          "draw_date": "2026-01-25",
          "full_number": "34967",
          "top3": "967",
          "top2": "67",
          "bottom2": "34"
        },
        {
          "draw_date": "2026-01-24",
          "full_number": "85783",
          "top3": "783",
          "top2": "83",
          "bottom2": "85"
        }
      ]
    },
    {
      "key": "hanoi",
      "name": "ฮานอย",
      "source_url": "https://www.raakaadee.com/ตรวจหวย-หุ้น/หวยฮานอยปกติ/",
      "fetched_at": "2026-01-26T17:05:33.298+00:00",
      "draws": [
        {
          "draw_date": "2026-01-25",
          "full_number": "99360",
          "top3": "360",
          "top2": "60",
          "bottom2": "93"
        },
        {
          "draw_date": "2026-01-24",
          "full_number": "98960",
          "top3": "960",
          "top2": "60",
          "bottom2": "93"
        },
        {
          "draw_date": "2026-01-23",
          "full_number": "98113",
          "top3": "113",
          "top2": "13",
          "bottom2": "93"
        }
      ]
    }
  ]
}